ali_mqtt.py
ali_mqtt-0.1.0.data/scripts/ali_mqtt.py
ali_mqtt-0.1.0.dist-info/METADATA
ali_mqtt-0.1.0.dist-info/WHEEL
ali_mqtt-0.1.0.dist-info/top_level.txt
ali_mqtt-0.1.0.dist-info/RECORD
