Metadata-Version: 2.1
Name: ali-mqtt
Version: 0.1.0
Summary: MQTT auth info generator for Ali IoT
Home-page: https://github.com/twimicn/ali-mqtt
Author: IvanLuLyf
Author-email: me@ivanlu.cn
License: MIT
Platform: any
Classifier: Operating System :: OS Independent
Classifier: Intended Audience :: Developers
Classifier: License :: OSI Approved :: MIT License
Classifier: Programming Language :: Python :: 3
Classifier: Programming Language :: Python :: 3.4
Classifier: Programming Language :: Python :: 3.5
Classifier: Programming Language :: Python :: 3.6
Classifier: Programming Language :: Python :: 3.7
